{
  "main": {
    "id": "ad7a1774f1f11016",
    "type": "split",
    "children": [
      {
        "id": "24101cab3864342d",
        "type": "tabs",
        "children": [
          {
            "id": "c458fe7b9a2c6953",
            "type": "leaf",
            "state": {
              "type": "markdown",
              "state": {
                "file": "notes/kernel/RealMode.md",
                "mode": "source",
                "source": false
              }
            }
          },
          {
            "id": "48b17bf005198595",
            "type": "leaf",
            "state": {
              "type": "markdown",
              "state": {
                "file": "notes/kernel/Protected Mode.md",
                "mode": "source",
                "source": false
              }
            }
          }
        ],
        "currentTab": 1
      }
    ],
    "direction": "vertical"
  },
  "left": {
    "id": "40b8e6366b081d3a",
    "type": "split",
    "children": [
      {
        "id": "198965cc46b76300",
        "type": "tabs",
        "children": [
          {
            "id": "91cd0df6db8edef4",
            "type": "leaf",
            "state": {
              "type": "file-explorer",
              "state": {
                "sortOrder": "alphabetical"
              }
            }
          },
          {
            "id": "20747550ffbc8687",
            "type": "leaf",
            "state": {
              "type": "search",
              "state": {
                "query": "",
                "matchingCase": false,
                "explainSearch": false,
                "collapseAll": false,
                "extraContext": false,
                "sortOrder": "alphabetical"
              }
            }
          },
          {
            "id": "550b170b57f29b73",
            "type": "leaf",
            "state": {
              "type": "starred",
              "state": {}
            }
          }
        ]
      }
    ],
    "direction": "horizontal",
    "width": 300
  },
  "right": {
    "id": "fcecadcefe69b117",
    "type": "split",
    "children": [
      {
        "id": "def5d8c33d396316",
        "type": "tabs",
        "children": [
          {
            "id": "0bfe90edff0efb35",
            "type": "leaf",
            "state": {
              "type": "backlink",
              "state": {
                "file": "notes/kernel/Protected Mode.md",
                "collapseAll": false,
                "extraContext": false,
                "sortOrder": "alphabetical",
                "showSearch": false,
                "searchQuery": "",
                "backlinkCollapsed": false,
                "unlinkedCollapsed": true
              }
            }
          },
          {
            "id": "b504debe552eb3a1",
            "type": "leaf",
            "state": {
              "type": "outgoing-link",
              "state": {
                "file": "notes/kernel/Protected Mode.md",
                "linksCollapsed": false,
                "unlinkedCollapsed": true
              }
            }
          },
          {
            "id": "b9107ba613436d1e",
            "type": "leaf",
            "state": {
              "type": "tag",
              "state": {
                "sortOrder": "frequency",
                "useHierarchy": true
              }
            }
          },
          {
            "id": "585c51b5278ab6dd",
            "type": "leaf",
            "state": {
              "type": "outline",
              "state": {
                "file": "notes/kernel/Protected Mode.md"
              }
            }
          }
        ]
      }
    ],
    "direction": "horizontal",
    "width": 300,
    "collapsed": true
  },
  "active": "48b17bf005198595",
  "lastOpenFiles": [
    "notes/kernel/Pasted image 20221209233234.png",
    "notes/kernel/RealMode.md",
    "notes/Boot/BootProcess.md",
    "notes/kernel/Pasted image 20221209232924.png",
    "notes/kernel/ModuleTypes.md",
    "notes/kernel/Pasted image 20221209233304.png",
    "notes/kernel/Pasted image 20221209233031.png",
    "notes/kernel/Protected Mode.md",
    "notes/kernel/Interupts.md",
    "notes/kernel/device-Driver-V-kernel-Modules.md"
  ]
}